{
  "event_id": "118834",
  "time": "2022-10-28T08:04:33.910+07:00",
  "contest_time": "16:34:33.910",
  "state": {
    "started": "2022-10-27T15:30:00.000+07:00",
    "ended": "2022-10-27T17:45:00.000+07:00",
    "frozen": null,
    "thawed": null,
    "finalized": "2022-10-28T08:02:14.543+07:00",
    "end_of_updates": "2022-10-28T08:02:14.543+07:00"
  },
  "rows": [
    {
      "rank": 1,
      "team_id": "5025221085",
      "score": { "num_solved": 3, "total_time": 230 },
      "problems": [
        {
          "label": "Binary_Recursion",
          "problem_id": "Binary_Recursion",
          "num_judged": 1,
          "num_pending": 0,
          "solved": true,
          "first_to_solve": true,
          "time": 56
        },
        {
          "label": "HELP3.0",
          "problem_id": "HELP30",
          "num_judged": 0,
          "num_pending": 0,
          "solved": false,
          "first_to_solve": false
        },
        {
          "label": "STRCOMPRESS",
          "problem_id": "STRCOMPRESS",
          "num_judged": 1,
          "num_pending": 0,
          "solved": true,
          "first_to_solve": true,
          "time": 116
        },
        {
          "label": "TCenayang2",
          "problem_id": "TCenayang2",
          "num_judged": 1,
          "num_pending": 0,
          "solved": true,
          "first_to_solve": true,
          "time": 58
        }
      ]
    },
    {
      "rank": 2,
      "team_id": "5025221065",
      "score": { "num_solved": 3, "total_time": 318 },
      "problems": [
        {
          "label": "Binary_Recursion",
          "problem_id": "Binary_Recursion",
          "num_judged": 3,
          "num_pending": 0,
          "solved": true,
          "first_to_solve": false,
          "time": 91
        },
        {
          "label": "HELP3.0",
          "problem_id": "HELP30",
          "num_judged": 1,
          "num_pending": 0,
          "solved": true,
          "first_to_solve": true,
          "time": 50
        },
        {
          "label": "STRCOMPRESS",
          "problem_id": "STRCOMPRESS",
          "num_judged": 2,
          "num_pending": 0,
          "solved": true,
          "first_to_solve": false,
          "time": 117
        },
        {
          "label": "TCenayang2",
          "problem_id": "TCenayang2",
          "num_judged": 1,
          "num_pending": 0,
          "solved": false,
          "first_to_solve": false
        }
      ]
    },
    {
      "rank": 3,
      "team_id": "7221300092",
      "score": { "num_solved": 2, "total_time": 281 },
      "problems": [
        {
          "label": "Binary_Recursion",
          "problem_id": "Binary_Recursion",
          "num_judged": 5,
          "num_pending": 0,
          "solved": true,
          "first_to_solve": false,
          "time": 109
        },
        {
          "label": "HELP3.0",
          "problem_id": "HELP30",
          "num_judged": 3,
          "num_pending": 0,
          "solved": true,
          "first_to_solve": false,
          "time": 52
        },
        {
          "label": "STRCOMPRESS",
          "problem_id": "STRCOMPRESS",
          "num_judged": 1,
          "num_pending": 0,
          "solved": false,
          "first_to_solve": false
        },
        {
          "label": "TCenayang2",
          "problem_id": "TCenayang2",
          "num_judged": 0,
          "num_pending": 0,
          "solved": false,
          "first_to_solve": false
        }
      ]
    },
    {
      "rank": 4,
      "team_id": "5025221069",
      "score": { "num_solved": 1, "total_time": 64 },
      "problems": [
        {
          "label": "Binary_Recursion",
          "problem_id": "Binary_Recursion",
          "num_judged": 1,
          "num_pending": 0,
          "solved": true,
          "first_to_solve": false,
          "time": 64
        },
        {
          "label": "HELP3.0",
          "problem_id": "HELP30",
          "num_judged": 0,
          "num_pending": 0,
          "solved": false,
          "first_to_solve": false
        },
        {
          "label": "STRCOMPRESS",
          "problem_id": "STRCOMPRESS",
          "num_judged": 0,
          "num_pending": 0,
          "solved": false,
          "first_to_solve": false
        },
        {
          "label": "TCenayang2",
          "problem_id": "TCenayang2",
          "num_judged": 0,
          "num_pending": 0,
          "solved": false,
          "first_to_solve": false
        }
      ]
    },
    {
      "rank": 5,
      "team_id": "5025221098",
      "score": { "num_solved": 1, "total_time": 73 },
      "problems": [
        {
          "label": "Binary_Recursion",
          "problem_id": "Binary_Recursion",
          "num_judged": 0,
          "num_pending": 0,
          "solved": false,
          "first_to_solve": false
        },
        {
          "label": "HELP3.0",
          "problem_id": "HELP30",
          "num_judged": 1,
          "num_pending": 0,
          "solved": true,
          "first_to_solve": false,
          "time": 73
        },
        {
          "label": "STRCOMPRESS",
          "problem_id": "STRCOMPRESS",
          "num_judged": 0,
          "num_pending": 0,
          "solved": false,
          "first_to_solve": false
        },
        {
          "label": "TCenayang2",
          "problem_id": "TCenayang2",
          "num_judged": 0,
          "num_pending": 0,
          "solved": false,
          "first_to_solve": false
        }
      ]
    },
    {
      "rank": 6,
      "team_id": "5025221089",
      "score": { "num_solved": 1, "total_time": 87 },
      "problems": [
        {
          "label": "Binary_Recursion",
          "problem_id": "Binary_Recursion",
          "num_judged": 0,
          "num_pending": 0,
          "solved": false,
          "first_to_solve": false
        },
        {
          "label": "HELP3.0",
          "problem_id": "HELP30",
          "num_judged": 1,
          "num_pending": 0,
          "solved": true,
          "first_to_solve": false,
          "time": 87
        },
        {
          "label": "STRCOMPRESS",
          "problem_id": "STRCOMPRESS",
          "num_judged": 0,
          "num_pending": 0,
          "solved": false,
          "first_to_solve": false
        },
        {
          "label": "TCenayang2",
          "problem_id": "TCenayang2",
          "num_judged": 0,
          "num_pending": 0,
          "solved": false,
          "first_to_solve": false
        }
      ]
    },
    {
      "rank": 7,
      "team_id": "5025221096",
      "score": { "num_solved": 1, "total_time": 96 },
      "problems": [
        {
          "label": "Binary_Recursion",
          "problem_id": "Binary_Recursion",
          "num_judged": 0,
          "num_pending": 0,
          "solved": false,
          "first_to_solve": false
        },
        {
          "label": "HELP3.0",
          "problem_id": "HELP30",
          "num_judged": 1,
          "num_pending": 0,
          "solved": true,
          "first_to_solve": false,
          "time": 96
        },
        {
          "label": "STRCOMPRESS",
          "problem_id": "STRCOMPRESS",
          "num_judged": 0,
          "num_pending": 0,
          "solved": false,
          "first_to_solve": false
        },
        {
          "label": "TCenayang2",
          "problem_id": "TCenayang2",
          "num_judged": 0,
          "num_pending": 0,
          "solved": false,
          "first_to_solve": false
        }
      ]
    },
    {
      "rank": 8,
      "team_id": "5025221093",
      "score": { "num_solved": 1, "total_time": 105 },
      "problems": [
        {
          "label": "Binary_Recursion",
          "problem_id": "Binary_Recursion",
          "num_judged": 2,
          "num_pending": 0,
          "solved": true,
          "first_to_solve": false,
          "time": 85
        },
        {
          "label": "HELP3.0",
          "problem_id": "HELP30",
          "num_judged": 0,
          "num_pending": 0,
          "solved": false,
          "first_to_solve": false
        },
        {
          "label": "STRCOMPRESS",
          "problem_id": "STRCOMPRESS",
          "num_judged": 0,
          "num_pending": 0,
          "solved": false,
          "first_to_solve": false
        },
        {
          "label": "TCenayang2",
          "problem_id": "TCenayang2",
          "num_judged": 0,
          "num_pending": 0,
          "solved": false,
          "first_to_solve": false
        }
      ]
    },
    {
      "rank": 9,
      "team_id": "5025221110",
      "score": { "num_solved": 1, "total_time": 107 },
      "problems": [
        {
          "label": "Binary_Recursion",
          "problem_id": "Binary_Recursion",
          "num_judged": 6,
          "num_pending": 0,
          "solved": false,
          "first_to_solve": false
        },
        {
          "label": "HELP3.0",
          "problem_id": "HELP30",
          "num_judged": 1,
          "num_pending": 0,
          "solved": true,
          "first_to_solve": false,
          "time": 107
        },
        {
          "label": "STRCOMPRESS",
          "problem_id": "STRCOMPRESS",
          "num_judged": 0,
          "num_pending": 0,
          "solved": false,
          "first_to_solve": false
        },
        {
          "label": "TCenayang2",
          "problem_id": "TCenayang2",
          "num_judged": 1,
          "num_pending": 0,
          "solved": false,
          "first_to_solve": false
        }
      ]
    },
    {
      "rank": 10,
      "team_id": "5025221081",
      "score": { "num_solved": 1, "total_time": 109 },
      "problems": [
        {
          "label": "Binary_Recursion",
          "problem_id": "Binary_Recursion",
          "num_judged": 3,
          "num_pending": 0,
          "solved": true,
          "first_to_solve": false,
          "time": 69
        },
        {
          "label": "HELP3.0",
          "problem_id": "HELP30",
          "num_judged": 1,
          "num_pending": 0,
          "solved": false,
          "first_to_solve": false
        },
        {
          "label": "STRCOMPRESS",
          "problem_id": "STRCOMPRESS",
          "num_judged": 0,
          "num_pending": 0,
          "solved": false,
          "first_to_solve": false
        },
        {
          "label": "TCenayang2",
          "problem_id": "TCenayang2",
          "num_judged": 3,
          "num_pending": 0,
          "solved": false,
          "first_to_solve": false
        }
      ]
    },
    {
      "rank": 11,
      "team_id": "5025221078",
      "score": { "num_solved": 1, "total_time": 118 },
      "problems": [
        {
          "label": "Binary_Recursion",
          "problem_id": "Binary_Recursion",
          "num_judged": 1,
          "num_pending": 0,
          "solved": false,
          "first_to_solve": false
        },
        {
          "label": "HELP3.0",
          "problem_id": "HELP30",
          "num_judged": 1,
          "num_pending": 0,
          "solved": true,
          "first_to_solve": false,
          "time": 118
        },
        {
          "label": "STRCOMPRESS",
          "problem_id": "STRCOMPRESS",
          "num_judged": 0,
          "num_pending": 0,
          "solved": false,
          "first_to_solve": false
        },
        {
          "label": "TCenayang2",
          "problem_id": "TCenayang2",
          "num_judged": 2,
          "num_pending": 0,
          "solved": false,
          "first_to_solve": false
        }
      ]
    },
    {
      "rank": 12,
      "team_id": "5025221080",
      "score": { "num_solved": 1, "total_time": 134 },
      "problems": [
        {
          "label": "Binary_Recursion",
          "problem_id": "Binary_Recursion",
          "num_judged": 0,
          "num_pending": 0,
          "solved": false,
          "first_to_solve": false
        },
        {
          "label": "HELP3.0",
          "problem_id": "HELP30",
          "num_judged": 1,
          "num_pending": 0,
          "solved": true,
          "first_to_solve": false,
          "time": 134
        },
        {
          "label": "STRCOMPRESS",
          "problem_id": "STRCOMPRESS",
          "num_judged": 0,
          "num_pending": 0,
          "solved": false,
          "first_to_solve": false
        },
        {
          "label": "TCenayang2",
          "problem_id": "TCenayang2",
          "num_judged": 0,
          "num_pending": 0,
          "solved": false,
          "first_to_solve": false
        }
      ]
    },
    {
      "rank": 13,
      "team_id": "5025221112",
      "score": { "num_solved": 1, "total_time": 146 },
      "problems": [
        {
          "label": "Binary_Recursion",
          "problem_id": "Binary_Recursion",
          "num_judged": 2,
          "num_pending": 0,
          "solved": true,
          "first_to_solve": false,
          "time": 126
        },
        {
          "label": "HELP3.0",
          "problem_id": "HELP30",
          "num_judged": 0,
          "num_pending": 0,
          "solved": false,
          "first_to_solve": false
        },
        {
          "label": "STRCOMPRESS",
          "problem_id": "STRCOMPRESS",
          "num_judged": 0,
          "num_pending": 0,
          "solved": false,
          "first_to_solve": false
        },
        {
          "label": "TCenayang2",
          "problem_id": "TCenayang2",
          "num_judged": 1,
          "num_pending": 0,
          "solved": false,
          "first_to_solve": false
        }
      ]
    },
    {
      "rank": 14,
      "team_id": "5025221068",
      "score": { "num_solved": 0, "total_time": 0 },
      "problems": [
        {
          "label": "Binary_Recursion",
          "problem_id": "Binary_Recursion",
          "num_judged": 0,
          "num_pending": 0,
          "solved": false,
          "first_to_solve": false
        },
        {
          "label": "HELP3.0",
          "problem_id": "HELP30",
          "num_judged": 0,
          "num_pending": 0,
          "solved": false,
          "first_to_solve": false
        },
        {
          "label": "STRCOMPRESS",
          "problem_id": "STRCOMPRESS",
          "num_judged": 0,
          "num_pending": 0,
          "solved": false,
          "first_to_solve": false
        },
        {
          "label": "TCenayang2",
          "problem_id": "TCenayang2",
          "num_judged": 0,
          "num_pending": 0,
          "solved": false,
          "first_to_solve": false
        }
      ]
    },
    {
      "rank": 14,
      "team_id": "5025221319",
      "score": { "num_solved": 0, "total_time": 0 },
      "problems": [
        {
          "label": "Binary_Recursion",
          "problem_id": "Binary_Recursion",
          "num_judged": 4,
          "num_pending": 0,
          "solved": false,
          "first_to_solve": false
        },
        {
          "label": "HELP3.0",
          "problem_id": "HELP30",
          "num_judged": 0,
          "num_pending": 0,
          "solved": false,
          "first_to_solve": false
        },
        {
          "label": "STRCOMPRESS",
          "problem_id": "STRCOMPRESS",
          "num_judged": 0,
          "num_pending": 0,
          "solved": false,
          "first_to_solve": false
        },
        {
          "label": "TCenayang2",
          "problem_id": "TCenayang2",
          "num_judged": 0,
          "num_pending": 0,
          "solved": false,
          "first_to_solve": false
        }
      ]
    },
    {
      "rank": 14,
      "team_id": "7221300170",
      "score": { "num_solved": 0, "total_time": 0 },
      "problems": [
        {
          "label": "Binary_Recursion",
          "problem_id": "Binary_Recursion",
          "num_judged": 0,
          "num_pending": 0,
          "solved": false,
          "first_to_solve": false
        },
        {
          "label": "HELP3.0",
          "problem_id": "HELP30",
          "num_judged": 0,
          "num_pending": 0,
          "solved": false,
          "first_to_solve": false
        },
        {
          "label": "STRCOMPRESS",
          "problem_id": "STRCOMPRESS",
          "num_judged": 0,
          "num_pending": 0,
          "solved": false,
          "first_to_solve": false
        },
        {
          "label": "TCenayang2",
          "problem_id": "TCenayang2",
          "num_judged": 0,
          "num_pending": 0,
          "solved": false,
          "first_to_solve": false
        }
      ]
    },
    {
      "rank": 14,
      "team_id": "5025211264",
      "score": { "num_solved": 0, "total_time": 0 },
      "problems": [
        {
          "label": "Binary_Recursion",
          "problem_id": "Binary_Recursion",
          "num_judged": 0,
          "num_pending": 0,
          "solved": false,
          "first_to_solve": false
        },
        {
          "label": "HELP3.0",
          "problem_id": "HELP30",
          "num_judged": 2,
          "num_pending": 0,
          "solved": false,
          "first_to_solve": false
        },
        {
          "label": "STRCOMPRESS",
          "problem_id": "STRCOMPRESS",
          "num_judged": 0,
          "num_pending": 0,
          "solved": false,
          "first_to_solve": false
        },
        {
          "label": "TCenayang2",
          "problem_id": "TCenayang2",
          "num_judged": 0,
          "num_pending": 0,
          "solved": false,
          "first_to_solve": false
        }
      ]
    },
    {
      "rank": 14,
      "team_id": "5025221087",
      "score": { "num_solved": 0, "total_time": 0 },
      "problems": [
        {
          "label": "Binary_Recursion",
          "problem_id": "Binary_Recursion",
          "num_judged": 0,
          "num_pending": 0,
          "solved": false,
          "first_to_solve": false
        },
        {
          "label": "HELP3.0",
          "problem_id": "HELP30",
          "num_judged": 1,
          "num_pending": 0,
          "solved": false,
          "first_to_solve": false
        },
        {
          "label": "STRCOMPRESS",
          "problem_id": "STRCOMPRESS",
          "num_judged": 0,
          "num_pending": 0,
          "solved": false,
          "first_to_solve": false
        },
        {
          "label": "TCenayang2",
          "problem_id": "TCenayang2",
          "num_judged": 0,
          "num_pending": 0,
          "solved": false,
          "first_to_solve": false
        }
      ]
    },
    {
      "rank": 14,
      "team_id": "5025221083",
      "score": { "num_solved": 0, "total_time": 0 },
      "problems": [
        {
          "label": "Binary_Recursion",
          "problem_id": "Binary_Recursion",
          "num_judged": 0,
          "num_pending": 0,
          "solved": false,
          "first_to_solve": false
        },
        {
          "label": "HELP3.0",
          "problem_id": "HELP30",
          "num_judged": 0,
          "num_pending": 0,
          "solved": false,
          "first_to_solve": false
        },
        {
          "label": "STRCOMPRESS",
          "problem_id": "STRCOMPRESS",
          "num_judged": 0,
          "num_pending": 0,
          "solved": false,
          "first_to_solve": false
        },
        {
          "label": "TCenayang2",
          "problem_id": "TCenayang2",
          "num_judged": 0,
          "num_pending": 0,
          "solved": false,
          "first_to_solve": false
        }
      ]
    },
    {
      "rank": 14,
      "team_id": "5025221070",
      "score": { "num_solved": 0, "total_time": 0 },
      "problems": [
        {
          "label": "Binary_Recursion",
          "problem_id": "Binary_Recursion",
          "num_judged": 0,
          "num_pending": 0,
          "solved": false,
          "first_to_solve": false
        },
        {
          "label": "HELP3.0",
          "problem_id": "HELP30",
          "num_judged": 0,
          "num_pending": 0,
          "solved": false,
          "first_to_solve": false
        },
        {
          "label": "STRCOMPRESS",
          "problem_id": "STRCOMPRESS",
          "num_judged": 0,
          "num_pending": 0,
          "solved": false,
          "first_to_solve": false
        },
        {
          "label": "TCenayang2",
          "problem_id": "TCenayang2",
          "num_judged": 0,
          "num_pending": 0,
          "solved": false,
          "first_to_solve": false
        }
      ]
    },
    {
      "rank": 14,
      "team_id": "5025221094",
      "score": { "num_solved": 0, "total_time": 0 },
      "problems": [
        {
          "label": "Binary_Recursion",
          "problem_id": "Binary_Recursion",
          "num_judged": 0,
          "num_pending": 0,
          "solved": false,
          "first_to_solve": false
        },
        {
          "label": "HELP3.0",
          "problem_id": "HELP30",
          "num_judged": 0,
          "num_pending": 0,
          "solved": false,
          "first_to_solve": false
        },
        {
          "label": "STRCOMPRESS",
          "problem_id": "STRCOMPRESS",
          "num_judged": 0,
          "num_pending": 0,
          "solved": false,
          "first_to_solve": false
        },
        {
          "label": "TCenayang2",
          "problem_id": "TCenayang2",
          "num_judged": 0,
          "num_pending": 0,
          "solved": false,
          "first_to_solve": false
        }
      ]
    },
    {
      "rank": 14,
      "team_id": "5025221099",
      "score": { "num_solved": 0, "total_time": 0 },
      "problems": [
        {
          "label": "Binary_Recursion",
          "problem_id": "Binary_Recursion",
          "num_judged": 0,
          "num_pending": 0,
          "solved": false,
          "first_to_solve": false
        },
        {
          "label": "HELP3.0",
          "problem_id": "HELP30",
          "num_judged": 0,
          "num_pending": 0,
          "solved": false,
          "first_to_solve": false
        },
        {
          "label": "STRCOMPRESS",
          "problem_id": "STRCOMPRESS",
          "num_judged": 0,
          "num_pending": 0,
          "solved": false,
          "first_to_solve": false
        },
        {
          "label": "TCenayang2",
          "problem_id": "TCenayang2",
          "num_judged": 0,
          "num_pending": 0,
          "solved": false,
          "first_to_solve": false
        }
      ]
    },
    {
      "rank": 14,
      "team_id": "5025221071",
      "score": { "num_solved": 0, "total_time": 0 },
      "problems": [
        {
          "label": "Binary_Recursion",
          "problem_id": "Binary_Recursion",
          "num_judged": 0,
          "num_pending": 0,
          "solved": false,
          "first_to_solve": false
        },
        {
          "label": "HELP3.0",
          "problem_id": "HELP30",
          "num_judged": 0,
          "num_pending": 0,
          "solved": false,
          "first_to_solve": false
        },
        {
          "label": "STRCOMPRESS",
          "problem_id": "STRCOMPRESS",
          "num_judged": 0,
          "num_pending": 0,
          "solved": false,
          "first_to_solve": false
        },
        {
          "label": "TCenayang2",
          "problem_id": "TCenayang2",
          "num_judged": 0,
          "num_pending": 0,
          "solved": false,
          "first_to_solve": false
        }
      ]
    },
    {
      "rank": 14,
      "team_id": "5025221077",
      "score": { "num_solved": 0, "total_time": 0 },
      "problems": [
        {
          "label": "Binary_Recursion",
          "problem_id": "Binary_Recursion",
          "num_judged": 2,
          "num_pending": 0,
          "solved": false,
          "first_to_solve": false
        },
        {
          "label": "HELP3.0",
          "problem_id": "HELP30",
          "num_judged": 0,
          "num_pending": 0,
          "solved": false,
          "first_to_solve": false
        },
        {
          "label": "STRCOMPRESS",
          "problem_id": "STRCOMPRESS",
          "num_judged": 0,
          "num_pending": 0,
          "solved": false,
          "first_to_solve": false
        },
        {
          "label": "TCenayang2",
          "problem_id": "TCenayang2",
          "num_judged": 0,
          "num_pending": 0,
          "solved": false,
          "first_to_solve": false
        }
      ]
    },
    {
      "rank": 14,
      "team_id": "5025221111",
      "score": { "num_solved": 0, "total_time": 0 },
      "problems": [
        {
          "label": "Binary_Recursion",
          "problem_id": "Binary_Recursion",
          "num_judged": 0,
          "num_pending": 0,
          "solved": false,
          "first_to_solve": false
        },
        {
          "label": "HELP3.0",
          "problem_id": "HELP30",
          "num_judged": 0,
          "num_pending": 0,
          "solved": false,
          "first_to_solve": false
        },
        {
          "label": "STRCOMPRESS",
          "problem_id": "STRCOMPRESS",
          "num_judged": 0,
          "num_pending": 0,
          "solved": false,
          "first_to_solve": false
        },
        {
          "label": "TCenayang2",
          "problem_id": "TCenayang2",
          "num_judged": 0,
          "num_pending": 0,
          "solved": false,
          "first_to_solve": false
        }
      ]
    },
    {
      "rank": 14,
      "team_id": "5025221084",
      "score": { "num_solved": 0, "total_time": 0 },
      "problems": [
        {
          "label": "Binary_Recursion",
          "problem_id": "Binary_Recursion",
          "num_judged": 9,
          "num_pending": 0,
          "solved": false,
          "first_to_solve": false
        },
        {
          "label": "HELP3.0",
          "problem_id": "HELP30",
          "num_judged": 0,
          "num_pending": 0,
          "solved": false,
          "first_to_solve": false
        },
        {
          "label": "STRCOMPRESS",
          "problem_id": "STRCOMPRESS",
          "num_judged": 0,
          "num_pending": 0,
          "solved": false,
          "first_to_solve": false
        },
        {
          "label": "TCenayang2",
          "problem_id": "TCenayang2",
          "num_judged": 0,
          "num_pending": 0,
          "solved": false,
          "first_to_solve": false
        }
      ]
    },
    {
      "rank": 14,
      "team_id": "5025221066",
      "score": { "num_solved": 0, "total_time": 0 },
      "problems": [
        {
          "label": "Binary_Recursion",
          "problem_id": "Binary_Recursion",
          "num_judged": 0,
          "num_pending": 0,
          "solved": false,
          "first_to_solve": false
        },
        {
          "label": "HELP3.0",
          "problem_id": "HELP30",
          "num_judged": 1,
          "num_pending": 0,
          "solved": false,
          "first_to_solve": false
        },
        {
          "label": "STRCOMPRESS",
          "problem_id": "STRCOMPRESS",
          "num_judged": 0,
          "num_pending": 0,
          "solved": false,
          "first_to_solve": false
        },
        {
          "label": "TCenayang2",
          "problem_id": "TCenayang2",
          "num_judged": 0,
          "num_pending": 0,
          "solved": false,
          "first_to_solve": false
        }
      ]
    },
    {
      "rank": 14,
      "team_id": "5025221095",
      "score": { "num_solved": 0, "total_time": 0 },
      "problems": [
        {
          "label": "Binary_Recursion",
          "problem_id": "Binary_Recursion",
          "num_judged": 0,
          "num_pending": 0,
          "solved": false,
          "first_to_solve": false
        },
        {
          "label": "HELP3.0",
          "problem_id": "HELP30",
          "num_judged": 0,
          "num_pending": 0,
          "solved": false,
          "first_to_solve": false
        },
        {
          "label": "STRCOMPRESS",
          "problem_id": "STRCOMPRESS",
          "num_judged": 0,
          "num_pending": 0,
          "solved": false,
          "first_to_solve": false
        },
        {
          "label": "TCenayang2",
          "problem_id": "TCenayang2",
          "num_judged": 0,
          "num_pending": 0,
          "solved": false,
          "first_to_solve": false
        }
      ]
    },
    {
      "rank": 14,
      "team_id": "5025221074",
      "score": { "num_solved": 0, "total_time": 0 },
      "problems": [
        {
          "label": "Binary_Recursion",
          "problem_id": "Binary_Recursion",
          "num_judged": 3,
          "num_pending": 0,
          "solved": false,
          "first_to_solve": false
        },
        {
          "label": "HELP3.0",
          "problem_id": "HELP30",
          "num_judged": 0,
          "num_pending": 0,
          "solved": false,
          "first_to_solve": false
        },
        {
          "label": "STRCOMPRESS",
          "problem_id": "STRCOMPRESS",
          "num_judged": 0,
          "num_pending": 0,
          "solved": false,
          "first_to_solve": false
        },
        {
          "label": "TCenayang2",
          "problem_id": "TCenayang2",
          "num_judged": 0,
          "num_pending": 0,
          "solved": false,
          "first_to_solve": false
        }
      ]
    },
    {
      "rank": 14,
      "team_id": "5025221108",
      "score": { "num_solved": 0, "total_time": 0 },
      "problems": [
        {
          "label": "Binary_Recursion",
          "problem_id": "Binary_Recursion",
          "num_judged": 0,
          "num_pending": 0,
          "solved": false,
          "first_to_solve": false
        },
        {
          "label": "HELP3.0",
          "problem_id": "HELP30",
          "num_judged": 0,
          "num_pending": 0,
          "solved": false,
          "first_to_solve": false
        },
        {
          "label": "STRCOMPRESS",
          "problem_id": "STRCOMPRESS",
          "num_judged": 0,
          "num_pending": 0,
          "solved": false,
          "first_to_solve": false
        },
        {
          "label": "TCenayang2",
          "problem_id": "TCenayang2",
          "num_judged": 0,
          "num_pending": 0,
          "solved": false,
          "first_to_solve": false
        }
      ]
    },
    {
      "rank": 14,
      "team_id": "5025221079",
      "score": { "num_solved": 0, "total_time": 0 },
      "problems": [
        {
          "label": "Binary_Recursion",
          "problem_id": "Binary_Recursion",
          "num_judged": 0,
          "num_pending": 0,
          "solved": false,
          "first_to_solve": false
        },
        {
          "label": "HELP3.0",
          "problem_id": "HELP30",
          "num_judged": 0,
          "num_pending": 0,
          "solved": false,
          "first_to_solve": false
        },
        {
          "label": "STRCOMPRESS",
          "problem_id": "STRCOMPRESS",
          "num_judged": 0,
          "num_pending": 0,
          "solved": false,
          "first_to_solve": false
        },
        {
          "label": "TCenayang2",
          "problem_id": "TCenayang2",
          "num_judged": 0,
          "num_pending": 0,
          "solved": false,
          "first_to_solve": false
        }
      ]
    },
    {
      "rank": 14,
      "team_id": "7221300231",
      "score": { "num_solved": 0, "total_time": 0 },
      "problems": [
        {
          "label": "Binary_Recursion",
          "problem_id": "Binary_Recursion",
          "num_judged": 7,
          "num_pending": 0,
          "solved": false,
          "first_to_solve": false
        },
        {
          "label": "HELP3.0",
          "problem_id": "HELP30",
          "num_judged": 0,
          "num_pending": 0,
          "solved": false,
          "first_to_solve": false
        },
        {
          "label": "STRCOMPRESS",
          "problem_id": "STRCOMPRESS",
          "num_judged": 0,
          "num_pending": 0,
          "solved": false,
          "first_to_solve": false
        },
        {
          "label": "TCenayang2",
          "problem_id": "TCenayang2",
          "num_judged": 0,
          "num_pending": 0,
          "solved": false,
          "first_to_solve": false
        }
      ]
    },
    {
      "rank": 14,
      "team_id": "5025221091",
      "score": { "num_solved": 0, "total_time": 0 },
      "problems": [
        {
          "label": "Binary_Recursion",
          "problem_id": "Binary_Recursion",
          "num_judged": 0,
          "num_pending": 0,
          "solved": false,
          "first_to_solve": false
        },
        {
          "label": "HELP3.0",
          "problem_id": "HELP30",
          "num_judged": 0,
          "num_pending": 0,
          "solved": false,
          "first_to_solve": false
        },
        {
          "label": "STRCOMPRESS",
          "problem_id": "STRCOMPRESS",
          "num_judged": 0,
          "num_pending": 0,
          "solved": false,
          "first_to_solve": false
        },
        {
          "label": "TCenayang2",
          "problem_id": "TCenayang2",
          "num_judged": 0,
          "num_pending": 0,
          "solved": false,
          "first_to_solve": false
        }
      ]
    },
    {
      "rank": 14,
      "team_id": "5025221092",
      "score": { "num_solved": 0, "total_time": 0 },
      "problems": [
        {
          "label": "Binary_Recursion",
          "problem_id": "Binary_Recursion",
          "num_judged": 3,
          "num_pending": 0,
          "solved": false,
          "first_to_solve": false
        },
        {
          "label": "HELP3.0",
          "problem_id": "HELP30",
          "num_judged": 0,
          "num_pending": 0,
          "solved": false,
          "first_to_solve": false
        },
        {
          "label": "STRCOMPRESS",
          "problem_id": "STRCOMPRESS",
          "num_judged": 0,
          "num_pending": 0,
          "solved": false,
          "first_to_solve": false
        },
        {
          "label": "TCenayang2",
          "problem_id": "TCenayang2",
          "num_judged": 0,
          "num_pending": 0,
          "solved": false,
          "first_to_solve": false
        }
      ]
    },
    {
      "rank": 14,
      "team_id": "7221300048",
      "score": { "num_solved": 0, "total_time": 0 },
      "problems": [
        {
          "label": "Binary_Recursion",
          "problem_id": "Binary_Recursion",
          "num_judged": 0,
          "num_pending": 0,
          "solved": false,
          "first_to_solve": false
        },
        {
          "label": "HELP3.0",
          "problem_id": "HELP30",
          "num_judged": 0,
          "num_pending": 0,
          "solved": false,
          "first_to_solve": false
        },
        {
          "label": "STRCOMPRESS",
          "problem_id": "STRCOMPRESS",
          "num_judged": 0,
          "num_pending": 0,
          "solved": false,
          "first_to_solve": false
        },
        {
          "label": "TCenayang2",
          "problem_id": "TCenayang2",
          "num_judged": 0,
          "num_pending": 0,
          "solved": false,
          "first_to_solve": false
        }
      ]
    },
    {
      "rank": 14,
      "team_id": "5025221109",
      "score": { "num_solved": 0, "total_time": 0 },
      "problems": [
        {
          "label": "Binary_Recursion",
          "problem_id": "Binary_Recursion",
          "num_judged": 2,
          "num_pending": 0,
          "solved": false,
          "first_to_solve": false
        },
        {
          "label": "HELP3.0",
          "problem_id": "HELP30",
          "num_judged": 0,
          "num_pending": 0,
          "solved": false,
          "first_to_solve": false
        },
        {
          "label": "STRCOMPRESS",
          "problem_id": "STRCOMPRESS",
          "num_judged": 0,
          "num_pending": 0,
          "solved": false,
          "first_to_solve": false
        },
        {
          "label": "TCenayang2",
          "problem_id": "TCenayang2",
          "num_judged": 0,
          "num_pending": 0,
          "solved": false,
          "first_to_solve": false
        }
      ]
    },
    {
      "rank": 14,
      "team_id": "5025221076",
      "score": { "num_solved": 0, "total_time": 0 },
      "problems": [
        {
          "label": "Binary_Recursion",
          "problem_id": "Binary_Recursion",
          "num_judged": 0,
          "num_pending": 0,
          "solved": false,
          "first_to_solve": false
        },
        {
          "label": "HELP3.0",
          "problem_id": "HELP30",
          "num_judged": 1,
          "num_pending": 0,
          "solved": false,
          "first_to_solve": false
        },
        {
          "label": "STRCOMPRESS",
          "problem_id": "STRCOMPRESS",
          "num_judged": 0,
          "num_pending": 0,
          "solved": false,
          "first_to_solve": false
        },
        {
          "label": "TCenayang2",
          "problem_id": "TCenayang2",
          "num_judged": 0,
          "num_pending": 0,
          "solved": false,
          "first_to_solve": false
        }
      ]
    },
    {
      "rank": 14,
      "team_id": "5025221067",
      "score": { "num_solved": 0, "total_time": 0 },
      "problems": [
        {
          "label": "Binary_Recursion",
          "problem_id": "Binary_Recursion",
          "num_judged": 1,
          "num_pending": 0,
          "solved": false,
          "first_to_solve": false
        },
        {
          "label": "HELP3.0",
          "problem_id": "HELP30",
          "num_judged": 0,
          "num_pending": 0,
          "solved": false,
          "first_to_solve": false
        },
        {
          "label": "STRCOMPRESS",
          "problem_id": "STRCOMPRESS",
          "num_judged": 0,
          "num_pending": 0,
          "solved": false,
          "first_to_solve": false
        },
        {
          "label": "TCenayang2",
          "problem_id": "TCenayang2",
          "num_judged": 0,
          "num_pending": 0,
          "solved": false,
          "first_to_solve": false
        }
      ]
    },
    {
      "rank": 14,
      "team_id": "5025221318",
      "score": { "num_solved": 0, "total_time": 0 },
      "problems": [
        {
          "label": "Binary_Recursion",
          "problem_id": "Binary_Recursion",
          "num_judged": 0,
          "num_pending": 0,
          "solved": false,
          "first_to_solve": false
        },
        {
          "label": "HELP3.0",
          "problem_id": "HELP30",
          "num_judged": 0,
          "num_pending": 0,
          "solved": false,
          "first_to_solve": false
        },
        {
          "label": "STRCOMPRESS",
          "problem_id": "STRCOMPRESS",
          "num_judged": 2,
          "num_pending": 0,
          "solved": false,
          "first_to_solve": false
        },
        {
          "label": "TCenayang2",
          "problem_id": "TCenayang2",
          "num_judged": 0,
          "num_pending": 0,
          "solved": false,
          "first_to_solve": false
        }
      ]
    },
    {
      "rank": 14,
      "team_id": "5025221088",
      "score": { "num_solved": 0, "total_time": 0 },
      "problems": [
        {
          "label": "Binary_Recursion",
          "problem_id": "Binary_Recursion",
          "num_judged": 3,
          "num_pending": 0,
          "solved": false,
          "first_to_solve": false
        },
        {
          "label": "HELP3.0",
          "problem_id": "HELP30",
          "num_judged": 0,
          "num_pending": 0,
          "solved": false,
          "first_to_solve": false
        },
        {
          "label": "STRCOMPRESS",
          "problem_id": "STRCOMPRESS",
          "num_judged": 0,
          "num_pending": 0,
          "solved": false,
          "first_to_solve": false
        },
        {
          "label": "TCenayang2",
          "problem_id": "TCenayang2",
          "num_judged": 0,
          "num_pending": 0,
          "solved": false,
          "first_to_solve": false
        }
      ]
    },
    {
      "rank": 14,
      "team_id": "5025221073",
      "score": { "num_solved": 0, "total_time": 0 },
      "problems": [
        {
          "label": "Binary_Recursion",
          "problem_id": "Binary_Recursion",
          "num_judged": 0,
          "num_pending": 0,
          "solved": false,
          "first_to_solve": false
        },
        {
          "label": "HELP3.0",
          "problem_id": "HELP30",
          "num_judged": 0,
          "num_pending": 0,
          "solved": false,
          "first_to_solve": false
        },
        {
          "label": "STRCOMPRESS",
          "problem_id": "STRCOMPRESS",
          "num_judged": 0,
          "num_pending": 0,
          "solved": false,
          "first_to_solve": false
        },
        {
          "label": "TCenayang2",
          "problem_id": "TCenayang2",
          "num_judged": 0,
          "num_pending": 0,
          "solved": false,
          "first_to_solve": false
        }
      ]
    }
  ]
}
